Metadata-Version: 2.2
Name: py-reform
Version: 0.1.3
Summary: A Python library for dewarping/straightening/reformatting document images and PDFs
Home-page: https://github.com/jsoma/py-reform
Author: Jonathan Soma
Author-email: jonathan.soma@gmail.com
Classifier: Programming Language :: Python :: 3
Classifier: Programming Language :: Python :: 3.8
Classifier: Programming Language :: Python :: 3.9
Classifier: Programming Language :: Python :: 3.10
Classifier: License :: OSI Approved :: MIT License
Classifier: Operating System :: OS Independent
Classifier: Topic :: Scientific/Engineering :: Image Processing
Classifier: Topic :: Multimedia :: Graphics
Requires-Python: >=3.8
License-File: LICENSE
Requires-Dist: pillow<12.0.0,>=9.0.0
Requires-Dist: numpy<2.0.0,>=1.20.0
Requires-Dist: tqdm<5.0.0,>=4.60.0
Requires-Dist: pypdfium2<5.0.0,>=4.0.0
Requires-Dist: torch<3.0.0,>=1.10.0
Requires-Dist: deskew>=1.0.0
Provides-Extra: dev
Requires-Dist: pytest>=7.0.0; extra == "dev"
Requires-Dist: black>=22.0.0; extra == "dev"
Requires-Dist: isort>=5.10.0; extra == "dev"
Requires-Dist: mypy>=0.950; extra == "dev"
Dynamic: author
Dynamic: author-email
Dynamic: classifier
Dynamic: description
Dynamic: description-content-type
Dynamic: home-page
Dynamic: provides-extra
Dynamic: requires-dist
Dynamic: requires-python
Dynamic: summary
